celery_worker_healthcheck/__init__.py
celery_worker_healthcheck/test/__init__.py
celery_worker_healthcheck/test/test_healthcheck.py
celery_worker_healthcheck/test/fixture/__init__.py
celery_worker_healthcheck/test/fixture/app.py
celery_worker_healthcheck/test/fixture/conf.py
celery_worker_healthcheck-1.0.0.dist-info/METADATA
celery_worker_healthcheck-1.0.0.dist-info/WHEEL
celery_worker_healthcheck-1.0.0.dist-info/licenses/LICENSE
celery_worker_healthcheck-1.0.0.dist-info/RECORD
