Metadata-Version: 2.4
Name: celery_worker_healthcheck
Version: 1.0.0
Summary: HTTP endpoint that counts ready celery workers
Project-URL: repository, https://github.com/ZeitOnline/celery_worker_healthcheck
Author-email: Zeit Online <zon-backend@zeit.de>
License: BSD-3-Clause
License-File: LICENSE
Requires-Python: >=3.7
Requires-Dist: celery
Provides-Extra: test
Requires-Dist: pytest; extra == 'test'
Requires-Dist: requests; extra == 'test'
